angreal-2.7.2.dist-info/METADATA
angreal-2.7.2.dist-info/WHEEL
angreal-2.7.2.dist-info/entry_points.txt
angreal/__init__.py
angreal/angreal.cp313-win_amd64.pyd
angreal-2.7.2.dist-info/RECORD
